{
  "users": [
    {
      "id": 7,
      "username": "json-server",
      "sex": "1",
      "age": "18"
    },
    {
      "id": 9,
      "username": "json-server",
      "sex": "1",
      "age": "18"
    },
    {
      "id": 10,
      "username": "as",
      "sex": "0112222",
      "age": "18"
    },
    {
      "username": "22",
      "age": "22",
      "sex": "1212",
      "id": 11
    },
    {
      "username": "3123",
      "age": "12312",
      "sex": "123123",
      "id": 12
    },
    {
      "username": "12312",
      "age": "123",
      "sex": "123123",
      "id": 13
    },
    {
      "username": "312311",
      "age": "123",
      "sex": "123123",
      "id": 14
    },
    {
      "username": "3123",
      "age": "123123",
      "sex": "123123",
      "id": 15
    },
    {
      "username": "123123",
      "age": "123123",
      "sex": "1231231",
      "id": 16
    },
    {
      "username": "123123",
      "age": "123123",
      "sex": "123123123",
      "id": 17
    },
    {
      "username": "3123123",
      "age": "123123",
      "sex": "123123123",
      "id": 18
    },
    {
      "username": "122",
      "age": "333",
      "sex": "212",
      "id": 19
    },
    {
      "username": "11",
      "age": "222",
      "sex": "111",
      "id": 20
    },
    {
      "username": "11",
      "age": "11",
      "sex": "222",
      "id": 21
    }
  ],
  "comments": [
    {
      "id": 1,
      "body": "some comment",
      "postId": 1
    }
  ],
  "profile": {
    "name": "typicode"
  }
}